PyDynamicaLC/PyDynamicaLC.py
PyDynamicaLC/__init__.py
pydynamicalc-0.0.2.dist-info/METADATA
pydynamicalc-0.0.2.dist-info/WHEEL
pydynamicalc-0.0.2.dist-info/top_level.txt
pydynamicalc-0.0.2.dist-info/RECORD
