Metadata-Version: 2.1
Name: pydynamicalc
Version: 0.0.2
Summary: Pythonic photodynamical model generator, using three different configurations (quasi-circular, eccentric and osculating), in addition - an MCMC-coupled version is also provided, which allows optimization of planetary masses and eccentricities
Home-page: https://github.com/AstroGidi/PyDynamicaLC
Author: Gideon Yoffe
Author-email: yoffe@mpia.de
License: Weizmann Institute of Science
Platform: UNKNOWN
Requires-Dist: ttvfaster
Requires-Dist: matplotlib
Requires-Dist: numpy
Requires-Dist: scipy
Requires-Dist: pyastronomy
Requires-Dist: pymultinest
Requires-Dist: corner
Requires-Dist: wheel
